databricks/__init__.py
databricks/bundles/__init__.py
databricks/bundles/build.py
databricks/bundles/py.typed
databricks/bundles/version.py
databricks/bundles/core/__init__.py
databricks/bundles/core/_bundle.py
databricks/bundles/core/_diagnostics.py
databricks/bundles/core/_load.py
databricks/bundles/core/_location.py
databricks/bundles/core/_resource.py
databricks/bundles/core/_resource_mutator.py
databricks/bundles/core/_resource_type.py
databricks/bundles/core/_resources.py
databricks/bundles/core/_transform.py
databricks/bundles/core/_transform_to_json.py
databricks/bundles/core/_variable.py
databricks/bundles/jobs/__init__.py
databricks/bundles/jobs/_models/adlsgen2_info.py
databricks/bundles/jobs/_models/authentication_method.py
databricks/bundles/jobs/_models/auto_scale.py
databricks/bundles/jobs/_models/aws_attributes.py
databricks/bundles/jobs/_models/aws_availability.py
databricks/bundles/jobs/_models/azure_attributes.py
databricks/bundles/jobs/_models/azure_availability.py
databricks/bundles/jobs/_models/clean_rooms_notebook_task.py
databricks/bundles/jobs/_models/clients_types.py
databricks/bundles/jobs/_models/cluster_log_conf.py
databricks/bundles/jobs/_models/cluster_spec.py
databricks/bundles/jobs/_models/compute_config.py
databricks/bundles/jobs/_models/condition.py
databricks/bundles/jobs/_models/condition_task.py
databricks/bundles/jobs/_models/condition_task_op.py
databricks/bundles/jobs/_models/continuous.py
databricks/bundles/jobs/_models/cron_schedule.py
databricks/bundles/jobs/_models/dashboard_task.py
databricks/bundles/jobs/_models/data_security_mode.py
databricks/bundles/jobs/_models/dbfs_storage_info.py
databricks/bundles/jobs/_models/dbt_platform_task.py
databricks/bundles/jobs/_models/dbt_task.py
databricks/bundles/jobs/_models/docker_basic_auth.py
databricks/bundles/jobs/_models/docker_image.py
databricks/bundles/jobs/_models/ebs_volume_type.py
databricks/bundles/jobs/_models/environment.py
databricks_bundles-0.283.0.dist-info/licenses/LICENSE
databricks_bundles-0.283.0.dist-info/WHEEL
databricks_bundles-0.283.0.dist-info/METADATA
databricks_bundles-0.283.0.dist-info/RECORD
