Metadata-Version: 2.4
Name: databricks-bundles
Version: 0.283.0
Summary: Python support for Databricks Asset Bundles
Author-email: Gleb Kanterov <gleb.kanterov@databricks.com>
Requires-Python: >=3.10
License-File: LICENSE
